{
    "applinks": {
        "apps": [],
        "details": [
            {
                "appID": "64ZXQ8664V.com.linkedin.recruiter.enterprise",
                "paths": [
                    "/cap/comm/*",
                    "/comm/cap/comm/*",
                    "/recruiter/mailbox/*",
                    "/talent/profile/*",
                    "/e/v2/talent/*",
                    "/talent/redirect/batchReview",
                    "/comm/talent/redirect/batchReview",
                    "/comm/recruiter/mailbox/conversation/*"
                ]
            },
            {
                "appID": "8AXPVS6C36.com.linkedin.recruiter",
                "paths": [
                    "/cap/comm/*",
                    "/comm/cap/comm/*",
                    "/recruiter/mailbox/*",
                    "/talent/profile/*",
                    "/e/v2/talent/*",
                    "/talent/redirect/batchReview",
                    "/comm/talent/redirect/batchReview",
                    "/comm/recruiter/mailbox/conversation/*"
                ]
            },
            {
                "appID": "277WVWYGVH.com.linkedin.LighthouseEnterprise",
                "paths": [
                    "/sales/*",
                    "/e/v2/sales/*"
                ]
            },
            {
                "appID": "8AXPVS6C36.com.linkedin.Lighthouse",
                "paths": [
                    "/sales/*",
                    "/e/v2/sales/*"
                ]
            },
            {
                "appID": "8AXPVS6C36.com.linkedin.Coworkers",
                "paths": [
                    "/lookup/*"
                ]
            },
            {
                "appID": "277WVWYGVH.com.linkedin.LinkedIn.enterprise",
                "paths": [
                    "/test/",
                    "/comm/m/",
                    "/comm/",
                    "/m/",
                    "/",
                    "/e/v2/pulse",
                    "/e/v2/newsle",
                    "/comm/feed",
                    "/feed",
                    "/comm/m/feed",
                    "/m/feed",
                    "/comm/feed/share",
                    "/feed/share",
                    "/m/feed/share",
                    "/comm/m/feed/share",
                    "/feed/update/*",
                    "/comm/feed/update/*",
                    "/comm/m/feed/update/*",
                    "/m/feed/update/*",
                    "/posts/*",
                    "/comm/posts/*",
                    "/comm/m/posts/*",
                    "/m/posts/*",
                    "/comm/feed/update/*/likes",
                    "/feed/update/*/likes",
                    "/m/feed/update/*/likes",
                    "/comm/m/feed/update/*/likes",
                    "/comm/feed/update/*/reshare",
                    "/feed/update/*/reshare",
                    "/m/feed/update/*/reshare",
                    "/comm/m/feed/update/*/reshare",
                    "/feed/update/*/rmview",
                    "/comm/feed/update/*/rmview",
                    "/m/feed/update/*/rmview",
                    "/comm/m/feed/update/*/rmview",
                    "/feed/follow",
                    "/feed/follow/confirmation",
                    "/feed/followers",
                    "/feed/news/*",
                    "/m/feed/news/*",
                    "/comm/feed/news/*",
                    "/comm/m/feed/news/*",
                    "/comm/news/story/*",
                    "/comm/m/news/story/*",
                    "/feed/topic/*",
                    "/m/feed/topic/*",
                    "/comm/feed/topic/*",
                    "/comm/m/feed/topic/*",
                    "/feed/hashtag/*",
                    "/m/feed/hashtag/*",
                    "/comm/feed/hashtag/*",
                    "/comm/m/feed/hashtag/*",
                    "/feed/sponsored-update/*",
                    "/leadGenForm/*",
                    "/fetch/enter-flow",
                    "/fetch/inviteAfterAcceptLanding",
                    "/comm/groups*",
                    "/groups*",
                    "/m/in/*",
                    "/comm/m/in/*",
                    "/in/*",
                    "/comm/in/*",
                    "/comm/job/home",
                    "/comm/jobs",
                    "/jobs",
                    "/jobs/saved",
                    "/jobs/jobsForYou",
                    "NOT /jobs/browse/*",
                    "/jobs/*-jobs",
                    "/jobs/*-jobs-*",
                    "/jobs/alerts",
                    "/comm/jobs/alerts",
                    "/jobs/alert-expansion-jam",
                    "/comm/jobs/alert-expansion-jam",
                    "/jobs/alert-expansion-jserp",
                    "/comm/jobs/alert-expansion-jserp",
                    "/jobs/jobs-in-*",
                    "/jobs/referrals/*",
                    "/comm/jobs/referrals/*",
                    "/comm/jobs/view/*",
                    "/jobs/view/*",
                    "/jobs/cap/view/*",
                    "/jobs2/view/*",
                    "/jobs/skills-path/*",
                    "/comm/jobs/skills-path/*",
                    "/skills-demonstration/*",
                    "/comm/skills-demonstration/*",
                    "/jobs/view/*/apply",
                    "/comm/jobs/view/*/apply",
                    "/jobs/search",
                    "/comm/jobs/search",
                    "/m/jobs/search",
                    "/comm/jobs/suggestions",
                    "/comm/jobs2/view/*",
                    "/comm/jobs/promo/wayin",
                    "/jobs/promo/wayin",
                    "/jobs/career-interests",
                    "/comm/jobs/career-interests",
                    "/jobs/launchpad-connect",
                    "/comm/jobs/launchpad-connect",
                    "/jobs/launchpad-success",
                    "/jobs/launchpad-update-profile",
                    "/comm/jobs/launchpad-update-profile",
                    "/jobs/search/onboarding-video",
                    "/comm/jobs/search/onboarding-video",
                    "/feed/launchpad",
                    "/comm/feed/launchpad",
                    "/notifications",
                    "/comm/notifications",
                    "/notifications/*",
                    "/comm/notifications/*",
                    "/appreciation/*",
                    "/onboarding",
                    "/onboarding/start",
                    "/comm/people/invite-accept",
                    "/comm/people/invite-ignore",
                    "/people/pymk",
                    "/comm/people/pymk",
                    "/comm/people/pymk/hub",
                    "/people/pymk/hub",
                    "/comm/people/send-invite",
                    "/comm/mynetwork/discovery-see-all",
                    "/mynetwork/discovery-see-all",
                    "/comm/mynetwork/pymk/*",
                    "/comm/payments/reacquireV2",
                    "/payments/reacquireV2",
                    "/premium/products",
                    "/premium/my-premium",
                    "/premium/cancellation",
                    "/premium/redeem/promo",
                    "/premium/redeem/gift",
                    "/comm/premium/products",
                    "/comm/premium/my-premium",
                    "/comm/premium/cancellation",
                    "/comm/profile/*",
                    "/profinder/projects-notification/*",
                    "/comm/psettings/email/confirm",
                    "NOT /pulse/topics/*",
                    "/pulse/*",
                    "/comm/pulse/*",
                    "/reg/enter-flow",
                    "/settings/emailConfirm",
                    "/settings/darkmode",
                    "/start/",
                    "/wvmx/profile",
                    "/comm/wvmx/profile",
                    "comm/hp",
                    "comm/hp/update/*",
                    "comm/nhome",
                    "comm/nhome/updates",
                    "NOT /m/company/*/*",
                    "NOT /comm/company/*/*",
                    "NOT /comm/m/company/*/*",
                    "NOT /m/company-beta/*/*",
                    "NOT /company-beta/*/*",
                    "NOT comm/company-beta/*/*",
                    "NOT comm/m/company-beta/*/*",
                    "/organization/*/campaign/*",
                    "/organization/*/campaign",
                    "/organization/*",
                    "/m/company/*",
                    "/comm/company/*/admin/overview",
                    "/company/*/admin/overview",
                    "/comm/company/*/admin/manage-admins",
                    "/company/*/admin/manage-admins",
                    "/company/*/campaign/*",
                    "/company/*/campaign",
                    "/company/*/life/*",
                    "/comm/company/*/life/*",
                    "/company/*/life",
                    "/comm/company/*/life",
                    "/company/*/jobs",
                    "/comm/company/*/jobs",
                    "/company/*/about",
                    "/company/*/people",
                    "/company/*/videos",
                    "/company/*/events",
                    "/company/*/posts",
                    "/company/*/mycompany/coworkercontent",
                    "/company/*",
                    "NOT /company/*/*",
                    "/comm/company/*",
                    "/comm/m/company/*",
                    "/m/company-beta/*",
                    "/company-beta/*",
                    "comm/company-beta/*",
                    "comm/m/company-beta/*",
                    "/products/*",
                    "products/*",
                    "feed-preferences/follow",
                    "feed-preferences",
                    "feed-preferences/unfollow",
                    "/comm/m/group/*",
                    "/comm/group/*",
                    "/m/group/*",
                    "group/*",
                    "groups/*",
                    "/m/groups/*",
                    "/comm/m/groups/*",
                    "hp",
                    "hp/update/*",
                    "/comm/m/job/*",
                    "job/*",
                    "/m/job/*",
                    "/comm/job/*",
                    "/m/job/home",
                    "/comm/m/job/home",
                    "job/home",
                    "launcher/xpromo_launcher_flagship",
                    "/comm/launcher/xpromo_launcher_flagship",
                    "/m/launcher/xpromo_launcher_flagship",
                    "/comm/m/launcher/xpromo_launcher_flagship",
                    "m/feed-preferences/follow",
                    "m/update/*",
                    "m/update/*/likes",
                    "m/update/*/reshare",
                    "m/update/*/rmview",
                    "/comm/me",
                    "/comm/m/me",
                    "me",
                    "/m/me",
                    "/m/me/profile-views",
                    "/me/profile-cover-story/create",
                    "/comm/me/profile-cover-story/create",
                    "/me/profile-video/create",
                    "/comm/me/profile-video/create",
                    "/comm/me/profile-views",
                    "me/profile-views",
                    "/comm/m/me/profile-views",
                    "me/recent-activity",
                    "/comm/me/recent-activity",
                    "/comm/m/me/recent-activity",
                    "/m/me/recent-activity",
                    "me/search-appearances",
                    "/m/me/search-appearances",
                    "/comm/me/search-appearances",
                    "/comm/messaging",
                    "/m/messaging",
                    "/comm/m/messaging",
                    "messaging",
                    "messaging/compose",
                    "/comm/messaging/compose",
                    "/comm/m/messaging/compose",
                    "/m/messaging/compose",
                    "/m/messaging/compose/*",
                    "/comm/messaging/compose/*",
                    "messaging/compose/*",
                    "/comm/m/messaging/compose/*",
                    "/comm/messaging/thread/*",
                    "/m/messaging/thread/*",
                    "messaging/thread/*",
                    "/comm/m/messaging/thread/*",
                    "/chat/*",
                    "/thread/*/conference/*",
                    "/comm/mynetwork",
                    "/m/mynetwork",
                    "/comm/m/mynetwork",
                    "mynetwork",
                    "mynetwork/heathrow-redirect",
                    "/comm/mynetwork/heathrow-redirect",
                    "/comm/m/mynetwork/heathrow-redirect",
                    "/m/mynetwork/heathrow-redirect",
                    "/comm/mynetwork/import-contacts",
                    "/comm/m/mynetwork/import-contacts",
                    "/m/mynetwork/import-contacts",
                    "mynetwork/import-contacts",
                    "/comm/mynetwork/import-contacts/results",
                    "/comm/m/mynetwork/import-contacts/results",
                    "/m/mynetwork/import-contacts/results",
                    "mynetwork/import-contacts/results",
                    "/comm/mynetwork/connection-suggestions",
                    "/comm/m/mynetwork/connection-suggestions",
                    "/m/mynetwork/connection-suggestions",
                    "mynetwork/connection-suggestions",
                    "/comm/m/mynetwork/invite-accept/invitationId/*/sharedKey/*",
                    "mynetwork/invite-accept/invitationId/*/sharedKey/*",
                    "/m/mynetwork/invite-accept/invitationId/*/sharedKey/*",
                    "/comm/mynetwork/invite-accept/invitationId/*/sharedKey/*",
                    "/comm/m/mynetwork/invite-ignore/invitationId/*/sharedKey/*",
                    "mynetwork/invite-ignore/invitationId/*/sharedKey/*",
                    "/m/mynetwork/invite-ignore/invitationId/*/sharedKey/*",
                    "/comm/mynetwork/invite-ignore/invitationId/*/sharedKey/*",
                    "/comm/m/mynetwork/send-invite/*",
                    "mynetwork/send-invite/*",
                    "/m/mynetwork/send-invite/*",
                    "/comm/mynetwork/send-invite/*",
                    "/build-relation",
                    "/build-relation/*",
                    "/comm/m/mynetwork/add-connections",
                    "mynetwork/add-connections",
                    "/m/mynetwork/add-connections",
                    "/comm/mynetwork/add-connections",
                    "mynetwork/invite-connect/connections",
                    "/m/mynetwork/invite-connect/connections",
                    "/comm/mynetwork/invite-connect/connections",
                    "/comm/m/mynetwork/invite-connect/connections",
                    "/m/mynetwork/invite-connect/invitations",
                    "/comm/m/mynetwork/invite-connect/invitations",
                    "mynetwork/invite-connect/invitations",
                    "/comm/mynetwork/invite-connect/invitations",
                    "mynetwork/discover-hub",
                    "/comm/mynetwork/discover-hub",
                    "nhome",
                    "nhome/updates",
                    "/m/profile/*",
                    "/comm/m/profile/*",
                    "/profile/*",
                    "/profile/add",
                    "/m/profile/add",
                    "/comm/m/profile/add",
                    "/in/me/add-edit/*",
                    "/in/me/details/*",
                    "/m/profile/edit",
                    "/comm/m/profile/edit",
                    "profile/edit",
                    "/comm/profile/edit",
                    "/m/profile/uedit",
                    "/comm/m/profile/uedit",
                    "profile/uedit",
                    "/comm/profile/uedit",
                    "/m/profile/edit/skills",
                    "profile/edit/skills",
                    "/comm/m/profile/edit/skills",
                    "/comm/profile/edit/skills",
                    "/comm/m/profile/guided/*",
                    "profile/guided/*",
                    "/comm/profile/guided/*",
                    "/m/profile/guided/*",
                    "/m/profile/pendingEndorsements",
                    "/comm/profile/pendingEndorsements",
                    "/comm/m/profile/pendingEndorsements",
                    "profile/pendingEndorsements",
                    "/pub/dir/*",
                    "recs/received",
                    "/m/recs/received",
                    "/comm/m/recs/received",
                    "recs/give",
                    "/m/recs/give",
                    "/comm/m/recs/give",
                    "/showcase/*",
                    "/showcase/*/about",
                    "/showcase/*/videos",
                    "/showcase/*/events",
                    "/showcase/*/posts",
                    "/profile-opportunities/job-opportunities",
                    "/comm/profile-opportunities/job-opportunities",
                    "/profile-opportunities/job-opportunities/edit",
                    "/comm/profile-opportunities/job-opportunities/edit",
                    "/comm/m/school/*",
                    "school/*",
                    "/comm/school/*",
                    "/m/school/*",
                    "/school/*/about",
                    "/school/*/people",
                    "/school/*/videos",
                    "/school/*/events",
                    "/school/*/posts",
                    "/comm/settings",
                    "/comm/m/settings",
                    "/m/settings",
                    "settings",
                    "/comm/settings/messages",
                    "/comm/m/settings/messages",
                    "settings/messages",
                    "/m/settings/messages",
                    "settings/privacy",
                    "psettings/privacy",
                    "/m/settings/privacy",
                    "/comm/settings/privacy",
                    "/comm/m/settings/privacy",
                    "/comm/share",
                    "/comm/m/share",
                    "share",
                    "/m/share",
                    "shareArticle",
                    "/cws/share",
                    "update/*",
                    "/comm/update/*",
                    "/comm/m/update/*",
                    "/m/update/*",
                    "update/*/likes",
                    "/m/update/*/likes",
                    "/comm/m/update/*/likes",
                    "/comm/update/*/likes",
                    "/m/update/*/reshare",
                    "/comm/m/update/*/reshare",
                    "/comm/update/*/reshare",
                    "update/*/reshare",
                    "/comm/m/update/*/rmview",
                    "/m/update/*/rmview",
                    "/comm/update/*/rmview",
                    "update/*/rmview",
                    "search/results/all/*",
                    "/m/search/results/all/*",
                    "/comm/search/results/all/*",
                    "/comm/m/search/results/all/*",
                    "search/results/content/*",
                    "/m/search/results/content/*",
                    "/comm/search/results/content/*",
                    "/comm/m/search/results/content/*",
                    "search/results/people/*",
                    "/m/search/results/people/*",
                    "/comm/m/search/results/people/*",
                    "/comm/search/results/people/*",
                    "search/results/index/*",
                    "/m/search/results/index/*",
                    "/comm/m/search/results/index/*",
                    "/comm/search/results/index/*",
                    "/events/*",
                    "/comm/events/*",
                    "/video/collection/*",
                    "/comm/video/collection/*",
                    "/comm/checkpoint/rp/password-reset-new",
                    "/video/live/*",
                    "/comm/video/live/*",
                    "/video/event/*",
                    "/stories/*",
                    "/comm/stories/*",
                    "/mynetwork/colleagues",
                    "/comm/mynetwork/colleagues",
                    "/service-marketplace/request-details",
                    "/talent/redirect/automatedSourcing",
                    "/comm/talent/redirect/automatedSourcing",
                    "/analytics/*",
                    "/interview-prep",
                    "/interview-prep/assessments/*",
                    "/interview-prep/c/*",
                    "/service-marketplace/create-request",
                    "/service-marketplace/create-project/*",
                    "/service-marketplace/projects/*",
                    "/service-marketplace/provider/*",
                    "/career-services/projects/*",
                    "/comm/service-marketplace/projects/*",
                    "/comm/career-services/projects/*",
                    "/services/page/*",
                    "/comm/services/page/*",
                    "/news/*",
                    "/hiring/jobs/*/detail",
                    "/comm/hiring/jobs/*/detail",
                    "/hiring/jobs/*/applicants/*/details",
                    "/comm/hiring/jobs/*/applicants/*/detail",
                    "/hiring/jobs/*/applicants",
                    "/comm/hiring/jobs/*/applicants",
                    "/comm/hiring/jobs/create",
                    "/job-posting",
                    "/comm/job-posting",
                    "/post-a-job",
                    "/comm/post-a-job",
                    "/smart-links/*",
                    "/newsletters/*",
                    "/signup/cold-join/*",
                    "/login/*",
                    "/my-items/posted-jobs",
                    "/my-items/posted-jobs/claim",
                    "/comm/my-items/posted-jobs/claim",
                    "/my-items/saved-jobs",
                    "/comm/my-items/saved-jobs",
                    "/my-items/projects",
                    "/hire/videointro/*",
                    "/mycompany/*",
                    "/room/*",
                    "/rooms/*",
                    "/premium/news-onboarding",
                    "/comm/premium/news-onboarding",
                    "/comm/jobs/collections/*",
                    "/jobs/collections/*",
                    "/discover",
                    "/comm/discover",
                    "/suggested-for-you/*",
                    "/comm/suggested-for-you/*",
                    "/m/suggested-for-you/*",
                    "/comm/m/suggested-for-you/*"
                ]
            },
            {
                "appID": "277WVWYGVH.com.linkedin.LinkedIn",
                "paths": [
                    "/comm/m/",
                    "/comm/",
                    "/m/",
                    "/",
                    "/company/*",
                    "/products/*",
                    "products/*",
                    "/e/v2/pulse",
                    "/e/v2/newsle",
                    "/comm/feed",
                    "/feed",
                    "/comm/m/feed",
                    "/m/feed",
                    "/comm/feed/share",
                    "/feed/share",
                    "/m/feed/share",
                    "/comm/m/feed/share",
                    "/feed/update/*",
                    "/comm/feed/update/*",
                    "/comm/m/feed/update/*",
                    "/m/feed/update/*",
                    "/posts/*",
                    "/comm/posts/*",
                    "/comm/m/posts/*",
                    "/m/posts/*",
                    "/comm/feed/update/*/likes",
                    "/feed/update/*/likes",
                    "/m/feed/update/*/likes",
                    "/comm/m/feed/update/*/likes",
                    "/comm/feed/update/*/reshare",
                    "/feed/update/*/reshare",
                    "/m/feed/update/*/reshare",
                    "/comm/m/feed/update/*/reshare",
                    "/feed/update/*/rmview",
                    "/comm/feed/update/*/rmview",
                    "/m/feed/update/*/rmview",
                    "/comm/m/feed/update/*/rmview",
                    "/feed/follow",
                    "/feed/follow/confirmation",
                    "/feed/followers",
                    "/feed/news/*",
                    "/m/feed/news/*",
                    "/comm/feed/news/*",
                    "/comm/m/feed/news/*",
                    "/comm/news/story/*",
                    "/comm/m/news/story/*",
                    "/feed/topic/*",
                    "/m/feed/topic/*",
                    "/comm/feed/topic/*",
                    "/comm/m/feed/topic/*",
                    "/feed/hashtag/*",
                    "/m/feed/hashtag/*",
                    "/comm/feed/hashtag/*",
                    "/comm/m/feed/hashtag/*",
                    "/feed/sponsored-update/*",
                    "/leadGenForm/*",
                    "/fetch/enter-flow",
                    "/fetch/inviteAfterAcceptLanding",
                    "/comm/groups*",
                    "/groups*",
                    "/m/in/*",
                    "/comm/m/in/*",
                    "/in/*",
                    "/comm/in/*",
                    "/comm/job/home",
                    "/comm/jobs",
                    "/jobs",
                    "/jobs/saved",
                    "/jobs/jobsForYou",
                    "NOT /jobs/browse/*",
                    "/jobs/*-jobs",
                    "/jobs/*-jobs-*",
                    "/jobs/alerts",
                    "/comm/jobs/alerts",
                    "/jobs/alert-expansion-jam",
                    "/comm/jobs/alert-expansion-jam",
                    "/jobs/alert-expansion-jserp",
                    "/comm/jobs/alert-expansion-jserp",
                    "/jobs/jobs-in-*",
                    "/jobs/referrals/*",
                    "/comm/jobs/referrals/*",
                    "/comm/jobs/view/*",
                    "/jobs/view/*",
                    "/jobs/cap/view/*",
                    "/jobs2/view/*",
                    "/comm/jobs2/view/*",
                    "/jobs/skills-path/*",
                    "/comm/jobs/skills-path/*",
                    "/skills-demonstration/*",
                    "/comm/skills-demonstration/*",
                    "/jobs/view/*/apply",
                    "/comm/jobs/view/*/apply",
                    "/jobs/search",
                    "/comm/jobs/search",
                    "/m/jobs/search",
                    "/comm/jobs/suggestions",
                    "/comm/jobs/promo/wayin",
                    "/jobs/promo/wayin",
                    "/jobs/career-interests",
                    "/comm/jobs/career-interests",
                    "/jobs/launchpad-connect",
                    "/comm/jobs/launchpad-connect",
                    "/jobs/launchpad-success",
                    "/jobs/launchpad-update-profile",
                    "/comm/jobs/launchpad-update-profile",
                    "/jobs/search/onboarding-video",
                    "/comm/jobs/search/onboarding-video",
                    "/feed/launchpad",
                    "/comm/feed/launchpad",
                    "/notifications",
                    "/comm/notifications",
                    "/notifications/*",
                    "/comm/notifications/*",
                    "/appreciation/*",
                    "/onboarding",
                    "/onboarding/start",
                    "/comm/people/invite-accept",
                    "/comm/people/invite-ignore",
                    "/people/pymk",
                    "/comm/people/pymk",
                    "/comm/people/pymk/hub",
                    "/people/pymk/hub",
                    "/comm/people/send-invite",
                    "/comm/mynetwork/discovery-see-all",
                    "/mynetwork/discovery-see-all",
                    "/comm/mynetwork/pymk/*",
                    "/comm/payments/reacquireV2",
                    "/payments/reacquireV2",
                    "/premium/products",
                    "/premium/my-premium",
                    "/premium/cancellation",
                    "/premium/redeem/promo",
                    "/premium/redeem/gift",
                    "/comm/premium/products",
                    "/comm/premium/my-premium",
                    "/comm/premium/cancellation",
                    "/comm/profile/*",
                    "/profinder/projects-notification/*",
                    "/comm/psettings/email/confirm",
                    "NOT /pulse/topics/*",
                    "/pulse/*",
                    "/comm/pulse/*",
                    "/reg/enter-flow",
                    "/settings/emailConfirm",
                    "/settings/darkmode",
                    "/start/",
                    "/wvmx/profile",
                    "/comm/wvmx/profile",
                    "comm/hp",
                    "comm/hp/update/*",
                    "comm/nhome",
                    "comm/nhome/updates",
                    "/organization/*/campaign/*",
                    "/organization/*/campaign",
                    "/organization/*",
                    "/m/company/*",
                    "/comm/company/*/admin/overview",
                    "/company/*/admin/overview",
                    "/comm/company/*/admin/manage-admins",
                    "/company/*/admin/manage-admins",
                    "/company/*/campaign/*",
                    "/company/*/campaign",
                    "/company/*/life/*",
                    "/comm/company/*/life/*",
                    "/company/*/life",
                    "/comm/company/*/life",
                    "/company/*/jobs",
                    "/comm/company/*/jobs",
                    "/company/*/about",
                    "/company/*/people",
                    "/company/*/videos",
                    "/company/*/events",
                    "/company/*/posts",
                    "/company/*/mycompany/coworkercontent",
                    "company/*",
                    "NOT /company/*/*",
                    "/comm/company/*",
                    "/comm/m/company/*",
                    "/m/company-beta/*",
                    "company-beta/*",
                    "/comm/company-beta/*",
                    "/comm/m/company-beta/*",
                    "feed-preferences/follow",
                    "feed-preferences",
                    "feed-preferences/unfollow",
                    "/comm/m/group/*",
                    "/comm/group/*",
                    "/m/group/*",
                    "group/*",
                    "groups/*",
                    "/m/groups/*",
                    "/comm/m/groups/*",
                    "hp",
                    "hp/update/*",
                    "/comm/m/job/*",
                    "job/*",
                    "/m/job/*",
                    "/comm/job/*",
                    "/m/job/home",
                    "/comm/m/job/home",
                    "job/home",
                    "launcher/xpromo_launcher_flagship",
                    "/comm/launcher/xpromo_launcher_flagship",
                    "/m/launcher/xpromo_launcher_flagship",
                    "/comm/m/launcher/xpromo_launcher_flagship",
                    "m/feed-preferences/follow",
                    "m/update/*",
                    "m/update/*/likes",
                    "m/update/*/reshare",
                    "m/update/*/rmview",
                    "/comm/me",
                    "/comm/m/me",
                    "me",
                    "/m/me",
                    "/m/me/profile-views",
                    "/me/profile-cover-story/create",
                    "/comm/me/profile-cover-story/create",
                    "/me/profile-video/create",
                    "/comm/me/profile-video/create",
                    "/comm/me/profile-views",
                    "me/profile-views",
                    "/comm/m/me/profile-views",
                    "/in/me/add-edit/*",
                    "/in/me/details/*",
                    "me/recent-activity",
                    "/comm/me/recent-activity",
                    "/comm/m/me/recent-activity",
                    "/m/me/recent-activity",
                    "me/search-appearances",
                    "/m/me/search-appearances",
                    "/comm/me/search-appearances",
                    "/comm/messaging",
                    "/m/messaging",
                    "/comm/m/messaging",
                    "messaging",
                    "messaging/compose",
                    "/comm/messaging/compose",
                    "/comm/m/messaging/compose",
                    "/m/messaging/compose",
                    "/m/messaging/compose/*",
                    "/comm/messaging/compose/*",
                    "messaging/compose/*",
                    "/comm/m/messaging/compose/*",
                    "/comm/messaging/thread/*",
                    "/m/messaging/thread/*",
                    "messaging/thread/*",
                    "/comm/m/messaging/thread/*",
                    "/chat/*",
                    "/thread/*/conference/*",
                    "/comm/mynetwork",
                    "/m/mynetwork",
                    "/comm/m/mynetwork",
                    "mynetwork",
                    "mynetwork/heathrow-redirect",
                    "/comm/mynetwork/heathrow-redirect",
                    "/comm/m/mynetwork/heathrow-redirect",
                    "/m/mynetwork/heathrow-redirect",
                    "/comm/mynetwork/import-contacts",
                    "/comm/m/mynetwork/import-contacts",
                    "/m/mynetwork/import-contacts",
                    "mynetwork/import-contacts",
                    "/comm/mynetwork/import-contacts/results",
                    "/comm/m/mynetwork/import-contacts/results",
                    "/m/mynetwork/import-contacts/results",
                    "mynetwork/import-contacts/results",
                    "/comm/mynetwork/connection-suggestions",
                    "/comm/m/mynetwork/connection-suggestions",
                    "/m/mynetwork/connection-suggestions",
                    "mynetwork/connection-suggestions",
                    "/comm/m/mynetwork/invite-accept/invitationId/*/sharedKey/*",
                    "mynetwork/invite-accept/invitationId/*/sharedKey/*",
                    "/m/mynetwork/invite-accept/invitationId/*/sharedKey/*",
                    "/comm/mynetwork/invite-accept/invitationId/*/sharedKey/*",
                    "/comm/m/mynetwork/invite-ignore/invitationId/*/sharedKey/*",
                    "mynetwork/invite-ignore/invitationId/*/sharedKey/*",
                    "/m/mynetwork/invite-ignore/invitationId/*/sharedKey/*",
                    "/comm/mynetwork/invite-ignore/invitationId/*/sharedKey/*",
                    "/comm/m/mynetwork/send-invite/*",
                    "mynetwork/send-invite/*",
                    "/m/mynetwork/send-invite/*",
                    "/comm/mynetwork/send-invite/*",
                    "/build-relation",
                    "/build-relation/*",
                    "/comm/m/mynetwork/add-connections",
                    "mynetwork/add-connections",
                    "/m/mynetwork/add-connections",
                    "/comm/mynetwork/add-connections",
                    "mynetwork/invite-connect/connections",
                    "/m/mynetwork/invite-connect/connections",
                    "/comm/mynetwork/invite-connect/connections",
                    "/comm/m/mynetwork/invite-connect/connections",
                    "/m/mynetwork/invite-connect/invitations",
                    "/comm/m/mynetwork/invite-connect/invitations",
                    "mynetwork/invite-connect/invitations",
                    "/comm/mynetwork/invite-connect/invitations",
                    "mynetwork/discover-hub",
                    "/comm/mynetwork/discover-hub",
                    "nhome",
                    "nhome/updates",
                    "/m/profile/*",
                    "/comm/m/profile/*",
                    "/profile/*",
                    "/profile/add",
                    "/m/profile/add",
                    "/comm/m/profile/add",
                    "/m/profile/edit",
                    "/comm/m/profile/edit",
                    "profile/edit",
                    "/comm/profile/edit",
                    "/m/profile/uedit",
                    "/comm/m/profile/uedit",
                    "profile/uedit",
                    "/comm/profile/uedit",
                    "/m/profile/edit/skills",
                    "profile/edit/skills",
                    "/comm/m/profile/edit/skills",
                    "/comm/profile/edit/skills",
                    "/comm/m/profile/guided/*",
                    "profile/guided/*",
                    "/comm/profile/guided/*",
                    "/m/profile/guided/*",
                    "/m/profile/pendingEndorsements",
                    "/comm/profile/pendingEndorsements",
                    "/comm/m/profile/pendingEndorsements",
                    "profile/pendingEndorsements",
                    "/pub/dir/*",
                    "recs/received",
                    "/m/recs/received",
                    "/comm/m/recs/received",
                    "recs/give",
                    "/m/recs/give",
                    "/comm/m/recs/give",
                    "/showcase/*",
                    "/showcase/*/about",
                    "/showcase/*/videos",
                    "/showcase/*/events",
                    "/showcase/*/posts",
                    "/profile-opportunities/job-opportunities",
                    "/comm/profile-opportunities/job-opportunities",
                    "/profile-opportunities/job-opportunities/edit",
                    "/comm/profile-opportunities/job-opportunities/edit",
                    "/comm/m/school/*",
                    "school/*",
                    "/comm/school/*",
                    "/m/school/*",
                    "/school/*/about",
                    "/school/*/people",
                    "/school/*/videos",
                    "/school/*/events",
                    "/school/*/posts",
                    "/comm/settings",
                    "/comm/m/settings",
                    "/m/settings",
                    "settings",
                    "/comm/settings/messages",
                    "/comm/m/settings/messages",
                    "settings/messages",
                    "/m/settings/messages",
                    "settings/privacy",
                    "psettings/privacy",
                    "/m/settings/privacy",
                    "/comm/settings/privacy",
                    "/comm/m/settings/privacy",
                    "/comm/share",
                    "/comm/m/share",
                    "share",
                    "/m/share",
                    "shareArticle",
                    "/cws/share",
                    "update/*",
                    "/comm/update/*",
                    "/comm/m/update/*",
                    "/m/update/*",
                    "update/*/likes",
                    "/m/update/*/likes",
                    "/comm/m/update/*/likes",
                    "/comm/update/*/likes",
                    "/m/update/*/reshare",
                    "/comm/m/update/*/reshare",
                    "/comm/update/*/reshare",
                    "update/*/reshare",
                    "/comm/m/update/*/rmview",
                    "/m/update/*/rmview",
                    "/comm/update/*/rmview",
                    "update/*/rmview",
                    "search/results/all/*",
                    "/m/search/results/all/*",
                    "/comm/search/results/all/*",
                    "/comm/m/search/results/all/*",
                    "search/results/content/*",
                    "/m/search/results/content/*",
                    "/comm/search/results/content/*",
                    "/comm/m/search/results/content/*",
                    "search/results/people/*",
                    "/m/search/results/people/*",
                    "/comm/m/search/results/people/*",
                    "/comm/search/results/people/*",
                    "search/results/index/*",
                    "/m/search/results/index/*",
                    "/comm/m/search/results/index/*",
                    "/comm/search/results/index/*",
                    "/events/*",
                    "/comm/events/*",
                    "/video/collection/*",
                    "/comm/video/collection/*",
                    "/comm/checkpoint/rp/password-reset-new",
                    "/video/live/*",
                    "/comm/video/live/*",
                    "/video/event/*",
                    "/stories/*",
                    "/comm/stories/*",
                    "/mynetwork/colleagues",
                    "/comm/mynetwork/colleagues",
                    "/service-marketplace/request-details",
                    "/talent/redirect/automatedSourcing",
                    "/comm/talent/redirect/automatedSourcing",
                    "/analytics/*",
                    "/interview-prep",
                    "/interview-prep/assessments/*",
                    "/interview-prep/c/*",
                    "/service-marketplace/create-request",
                    "/service-marketplace/create-project/*",
                    "/service-marketplace/projects/*",
                    "/service-marketplace/provider/*",
                    "/career-services/projects/*",
                    "/comm/service-marketplace/projects/*",
                    "/comm/career-services/projects/*",
                    "/services/page/*",
                    "/comm/services/page/*",
                    "/news/*",
                    "/hiring/jobs/*/detail",
                    "/comm/hiring/jobs/*/detail",
                    "/hiring/jobs/*/applicants/*/details",
                    "/comm/hiring/jobs/*/applicants/*/detail",
                    "/hiring/jobs/*/applicants",
                    "/comm/hiring/jobs/*/applicants",
                    "/comm/hiring/jobs/create",
                    "/job-posting",
                    "/comm/job-posting",
                    "/post-a-job",
                    "/comm/post-a-job",
                    "/smart-links/*",
                    "/newsletters/*",
                    "/signup/cold-join/*",
                    "/login/*",
                    "/my-items/posted-jobs",
                    "/my-items/posted-jobs/claim",
                    "/comm/my-items/posted-jobs/claim",
                    "/my-items/saved-jobs",
                    "/comm/my-items/saved-jobs",
                    "/my-items/projects",
                    "/mycompany/*",
                    "/safety/reports/*",
                    "/safety/reports",
                    "/room/*",
                    "/rooms/*",
                    "/premium/news-onboarding",
                    "/comm/premium/news-onboarding",
                    "/comm/jobs/collections/*",
                    "/jobs/collections/*",
                    "/discover",
                    "/comm/discover",
                    "/suggested-for-you/*",
                    "/comm/suggested-for-you/*",
                    "/m/suggested-for-you/*",
                    "/comm/m/suggested-for-you/*"
                ]
            },
            {
                "appID": "8AXPVS6C36.com.linkedin.LinkedIn",
                "paths": [
                    "/comm/m/",
                    "/comm/",
                    "/m/",
                    "/",
                    "/company/*",
                    "/products/*",
                    "products/*",
                    "/e/v2/pulse",
                    "/e/v2/newsle",
                    "/comm/feed",
                    "/feed",
                    "/comm/m/feed",
                    "/m/feed",
                    "/comm/feed/share",
                    "/feed/share",
                    "/m/feed/share",
                    "/comm/m/feed/share",
                    "/feed/update/*",
                    "/comm/feed/update/*",
                    "/comm/m/feed/update/*",
                    "/m/feed/update/*",
                    "/posts/*",
                    "/comm/posts/*",
                    "/comm/m/posts/*",
                    "/m/posts/*",
                    "/comm/feed/update/*/likes",
                    "/feed/update/*/likes",
                    "/m/feed/update/*/likes",
                    "/comm/m/feed/update/*/likes",
                    "/comm/feed/update/*/reshare",
                    "/feed/update/*/reshare",
                    "/m/feed/update/*/reshare",
                    "/comm/m/feed/update/*/reshare",
                    "/feed/update/*/rmview",
                    "/comm/feed/update/*/rmview",
                    "/m/feed/update/*/rmview",
                    "/comm/m/feed/update/*/rmview",
                    "/feed/news/*",
                    "/m/feed/news/*",
                    "/comm/feed/news/*",
                    "/comm/m/feed/news/*",
                    "/comm/news/story/*",
                    "/comm/m/news/story/*",
                    "/feed/topic/*",
                    "/m/feed/topic/*",
                    "/comm/feed/topic/*",
                    "/comm/m/feed/topic/*",
                    "/feed/hashtag/*",
                    "/m/feed/hashtag/*",
                    "/comm/feed/hashtag/*",
                    "/comm/m/feed/hashtag/*",
                    "/feed/sponsored-update/*",
                    "/leadGenForm/*",
                    "/fetch/enter-flow",
                    "/fetch/inviteAfterAcceptLanding",
                    "/comm/groups*",
                    "/groups*",
                    "/m/in/*",
                    "/comm/m/in/*",
                    "/in/*",
                    "/comm/in/*",
                    "/comm/job/home",
                    "/comm/jobs",
                    "/jobs",
                    "/jobs/saved",
                    "/jobs/jobsForYou",
                    "NOT /jobs/browse/*",
                    "/jobs/*-jobs",
                    "/jobs/*-jobs-*",
                    "/jobs/alerts",
                    "/comm/jobs/alerts",
                    "/jobs/alert-expansion-jam",
                    "/comm/jobs/alert-expansion-jam",
                    "/jobs/alert-expansion-jserp",
                    "/comm/jobs/alert-expansion-jserp",
                    "/jobs/jobs-in-*",
                    "/comm/jobs/view/*",
                    "/jobs/view/*",
                    "/jobs/cap/view/*",
                    "/jobs2/view/*",
                    "/jobs/referrals/*",
                    "/comm/jobs/referrals/*",
                    "/jobs/skills-path/*",
                    "/comm/jobs/skills-path/*",
                    "/skills-demonstration/*",
                    "/comm/skills-demonstration/*",
                    "/jobs/view/*/apply",
                    "/comm/jobs/view/*/apply",
                    "/jobs/search",
                    "/comm/jobs/search",
                    "/m/jobs/search",
                    "/comm/jobs/suggestions",
                    "/comm/jobs2/view/*",
                    "/comm/jobs/promo/wayin",
                    "/jobs/promo/wayin",
                    "/jobs/career-interests",
                    "/comm/jobs/career-interests",
                    "/jobs/launchpad-connect",
                    "/comm/jobs/launchpad-connect",
                    "/jobs/launchpad-success",
                    "/jobs/launchpad-update-profile",
                    "/comm/jobs/launchpad-update-profile",
                    "/jobs/search/onboarding-video",
                    "/comm/jobs/search/onboarding-video",
                    "/feed/launchpad",
                    "/comm/feed/launchpad",
                    "/notifications",
                    "/comm/notifications",
                    "/notifications/*",
                    "/comm/notifications/*",
                    "/appreciation/*",
                    "/onboarding",
                    "/onboarding/start",
                    "/comm/people/invite-accept",
                    "/comm/people/invite-ignore",
                    "/comm/people/send-invite",
                    "/comm/mynetwork/discovery-see-all",
                    "/mynetwork/discovery-see-all",
                    "/comm/mynetwork/pymk/*",
                    "/comm/payments/reacquireV2",
                    "/payments/reacquireV2",
                    "/premium/products",
                    "/premium/my-premium",
                    "/premium/cancellation",
                    "/premium/redeem/promo",
                    "/premium/redeem/gift",
                    "/comm/premium/products",
                    "/comm/premium/my-premium",
                    "/comm/premium/cancellation",
                    "/comm/profile/*",
                    "/profinder/projects-notification/*",
                    "/comm/psettings/email/confirm",
                    "NOT /pulse/topics/*",
                    "/pulse/*",
                    "/comm/pulse/*",
                    "/reg/enter-flow",
                    "/settings/emailConfirm",
                    "/settings/darkmode",
                    "/start/",
                    "/wvmx/profile",
                    "/comm/wvmx/profile",
                    "comm/hp",
                    "comm/hp/update/*",
                    "comm/nhome",
                    "comm/nhome/updates",
                    "/organization/*/campaign/*",
                    "/organization/*/campaign",
                    "/organization/*",
                    "/m/company/*",
                    "/comm/company/*/admin/overview",
                    "/company/*/admin/overview",
                    "/comm/company/*/admin/manage-admins",
                    "/company/*/admin/manage-admins",
                    "/company/*/campaign/*",
                    "/company/*/campaign",
                    "/company/*/life/*",
                    "/comm/company/*/life/*",
                    "/company/*/life",
                    "/comm/company/*/life",
                    "/company/*/jobs",
                    "/comm/company/*/jobs",
                    "/company/*/about",
                    "/company/*/people",
                    "/company/*/videos",
                    "/company/*/events",
                    "/company/*/posts",
                    "/company/*/mycompany/coworkercontent",
                    "company/*",
                    "NOT /company/*/*",
                    "/comm/company/*",
                    "/comm/m/company/*",
                    "/m/company-beta/*",
                    "company-beta/*",
                    "/comm/company-beta/*",
                    "/comm/m/company-beta/*",
                    "feed-preferences/follow",
                    "/comm/m/group/*",
                    "/comm/group/*",
                    "/m/group/*",
                    "group/*",
                    "groups/*",
                    "/m/groups/*",
                    "/comm/m/groups/*",
                    "hp",
                    "hp/update/*",
                    "/comm/m/job/*",
                    "job/*",
                    "/m/job/*",
                    "/comm/job/*",
                    "/m/job/home",
                    "/comm/m/job/home",
                    "job/home",
                    "launcher/xpromo_launcher_flagship",
                    "/comm/launcher/xpromo_launcher_flagship",
                    "/m/launcher/xpromo_launcher_flagship",
                    "/comm/m/launcher/xpromo_launcher_flagship",
                    "m/feed-preferences/follow",
                    "m/update/*",
                    "m/update/*/likes",
                    "m/update/*/reshare",
                    "m/update/*/rmview",
                    "/comm/me",
                    "/comm/m/me",
                    "me",
                    "/m/me",
                    "/m/me/profile-views",
                    "/me/profile-cover-story/create",
                    "/comm/me/profile-cover-story/create",
                    "/me/profile-video/create",
                    "/comm/me/profile-video/create",
                    "/comm/me/profile-views",
                    "me/profile-views",
                    "/comm/m/me/profile-views",
                    "me/recent-activity",
                    "/comm/me/recent-activity",
                    "/comm/m/me/recent-activity",
                    "/m/me/recent-activity",
                    "me/search-appearances",
                    "/m/me/search-appearances",
                    "/comm/me/search-appearances",
                    "/comm/messaging",
                    "/m/messaging",
                    "/comm/m/messaging",
                    "messaging",
                    "messaging/compose",
                    "/comm/messaging/compose",
                    "/comm/m/messaging/compose",
                    "/m/messaging/compose",
                    "/m/messaging/compose/*",
                    "/comm/messaging/compose/*",
                    "messaging/compose/*",
                    "/comm/m/messaging/compose/*",
                    "/comm/messaging/thread/*",
                    "/m/messaging/thread/*",
                    "messaging/thread/*",
                    "/comm/m/messaging/thread/*",
                    "/chat/*",
                    "/thread/*/conference/*",
                    "/comm/mynetwork",
                    "/m/mynetwork",
                    "/comm/m/mynetwork",
                    "mynetwork",
                    "mynetwork/heathrow-redirect",
                    "/comm/mynetwork/heathrow-redirect",
                    "/comm/m/mynetwork/heathrow-redirect",
                    "/m/mynetwork/heathrow-redirect",
                    "/comm/mynetwork/import-contacts",
                    "/comm/m/mynetwork/import-contacts",
                    "/m/mynetwork/import-contacts",
                    "mynetwork/import-contacts",
                    "/comm/mynetwork/import-contacts/results",
                    "/comm/m/mynetwork/import-contacts/results",
                    "/m/mynetwork/import-contacts/results",
                    "mynetwork/import-contacts/results",
                    "/comm/mynetwork/connection-suggestions",
                    "/comm/m/mynetwork/connection-suggestions",
                    "/m/mynetwork/connection-suggestions",
                    "mynetwork/connection-suggestions",
                    "/comm/m/mynetwork/invite-accept/invitationId/*/sharedKey/*",
                    "mynetwork/invite-accept/invitationId/*/sharedKey/*",
                    "/m/mynetwork/invite-accept/invitationId/*/sharedKey/*",
                    "/comm/mynetwork/invite-accept/invitationId/*/sharedKey/*",
                    "/comm/m/mynetwork/invite-ignore/invitationId/*/sharedKey/*",
                    "mynetwork/invite-ignore/invitationId/*/sharedKey/*",
                    "/m/mynetwork/invite-ignore/invitationId/*/sharedKey/*",
                    "/comm/mynetwork/invite-ignore/invitationId/*/sharedKey/*",
                    "/comm/m/mynetwork/send-invite/*",
                    "mynetwork/send-invite/*",
                    "/m/mynetwork/send-invite/*",
                    "/comm/mynetwork/send-invite/*",
                    "/build-relation",
                    "/build-relation/*",
                    "/comm/m/mynetwork/add-connections",
                    "mynetwork/add-connections",
                    "/m/mynetwork/add-connections",
                    "/comm/mynetwork/add-connections",
                    "mynetwork/invite-connect/connections",
                    "/m/mynetwork/invite-connect/connections",
                    "/comm/mynetwork/invite-connect/connections",
                    "/comm/m/mynetwork/invite-connect/connections",
                    "/m/mynetwork/invite-connect/invitations",
                    "/comm/m/mynetwork/invite-connect/invitations",
                    "mynetwork/invite-connect/invitations",
                    "/comm/mynetwork/invite-connect/invitations",
                    "mynetwork/discover-hub",
                    "/comm/mynetwork/discover-hub",
                    "nhome",
                    "nhome/updates",
                    "/m/profile/*",
                    "/comm/m/profile/*",
                    "/profile/*",
                    "/profile/add",
                    "/m/profile/add",
                    "/comm/m/profile/add",
                    "/m/profile/edit",
                    "/comm/m/profile/edit",
                    "profile/edit",
                    "/comm/profile/edit",
                    "/m/profile/uedit",
                    "/comm/m/profile/uedit",
                    "profile/uedit",
                    "/comm/profile/uedit",
                    "/m/profile/edit/skills",
                    "profile/edit/skills",
                    "/comm/m/profile/edit/skills",
                    "/comm/profile/edit/skills",
                    "/comm/m/profile/guided/*",
                    "profile/guided/*",
                    "/comm/profile/guided/*",
                    "/m/profile/guided/*",
                    "/m/profile/pendingEndorsements",
                    "/comm/profile/pendingEndorsements",
                    "/comm/m/profile/pendingEndorsements",
                    "profile/pendingEndorsements",
                    "/in/me/add-edit/*",
                    "/in/me/details/*",
                    "/pub/dir/*",
                    "recs/received",
                    "/m/recs/received",
                    "/comm/m/recs/received",
                    "recs/give",
                    "/m/recs/give",
                    "/comm/m/recs/give",
                    "/showcase/*",
                    "/showcase/*/about",
                    "/showcase/*/videos",
                    "/showcase/*/events",
                    "/showcase/*/posts",
                    "/profile-opportunities/job-opportunities",
                    "/comm/profile-opportunities/job-opportunities",
                    "/profile-opportunities/job-opportunities/edit",
                    "/comm/profile-opportunities/job-opportunities/edit",
                    "/comm/m/school/*",
                    "school/*",
                    "/comm/school/*",
                    "/m/school/*",
                    "/school/*/about",
                    "/school/*/people",
                    "/school/*/videos",
                    "/school/*/events",
                    "/school/*/posts",
                    "/comm/settings",
                    "/comm/m/settings",
                    "/m/settings",
                    "settings",
                    "/comm/settings/messages",
                    "/comm/m/settings/messages",
                    "settings/messages",
                    "/m/settings/messages",
                    "settings/privacy",
                    "psettings/privacy",
                    "/m/settings/privacy",
                    "/comm/settings/privacy",
                    "/comm/m/settings/privacy",
                    "/comm/share",
                    "/comm/m/share",
                    "share",
                    "/m/share",
                    "shareArticle",
                    "/cws/share",
                    "update/*",
                    "/comm/update/*",
                    "/comm/m/update/*",
                    "/m/update/*",
                    "update/*/likes",
                    "/m/update/*/likes",
                    "/comm/m/update/*/likes",
                    "/comm/update/*/likes",
                    "/m/update/*/reshare",
                    "/comm/m/update/*/reshare",
                    "/comm/update/*/reshare",
                    "update/*/reshare",
                    "/comm/m/update/*/rmview",
                    "/m/update/*/rmview",
                    "/comm/update/*/rmview",
                    "update/*/rmview",
                    "search/results/all/*",
                    "/m/search/results/all/*",
                    "/comm/search/results/all/*",
                    "/comm/m/search/results/all/*",
                    "search/results/content/*",
                    "/m/search/results/content/*",
                    "/comm/search/results/content/*",
                    "/comm/m/search/results/content/*",
                    "search/results/people/*",
                    "/m/search/results/people/*",
                    "/comm/m/search/results/people/*",
                    "/comm/search/results/people/*",
                    "search/results/index/*",
                    "/m/search/results/index/*",
                    "/comm/m/search/results/index/*",
                    "/comm/search/results/index/*",
                    "/events/*",
                    "/comm/events/*",
                    "/video/collection/*",
                    "/comm/video/collection/*",
                    "/comm/checkpoint/rp/password-reset-new",
                    "/video/live/*",
                    "/comm/video/live/*",
                    "/video/event/*",
                    "/stories/*",
                    "/comm/stories/*",
                    "/mynetwork/colleagues",
                    "/comm/mynetwork/colleagues",
                    "/service-marketplace/request-details",
                    "/talent/redirect/automatedSourcing",
                    "/comm/talent/redirect/automatedSourcing",
                    "/analytics/*",
                    "/interview-prep",
                    "/interview-prep/assessments/*",
                    "/interview-prep/c/*",
                    "/service-marketplace/create-request",
                    "/service-marketplace/create-project/*",
                    "/service-marketplace/projects/*",
                    "/service-marketplace/provider/*",
                    "/career-services/projects/*",
                    "/comm/service-marketplace/projects/*",
                    "/comm/career-services/projects/*",
                    "/services/page/*",
                    "/comm/services/page/*",
                    "/news/*",
                    "/hiring/jobs/*/detail",
                    "/comm/hiring/jobs/*/detail",
                    "/hiring/jobs/*/applicants/*/details",
                    "/comm/hiring/jobs/*/applicants/*/detail",
                    "/hiring/jobs/*/applicants",
                    "/comm/hiring/jobs/*/applicants",
                    "/comm/hiring/jobs/create",
                    "/job-posting",
                    "/comm/job-posting",
                    "/post-a-job",
                    "/comm/post-a-job",
                    "/smart-links/*",
                    "/newsletters/*",
                    "/signup/cold-join/*",
                    "/login/*",
                    "/my-items/posted-jobs",
                    "/my-items/posted-jobs/claim",
                    "/comm/my-items/posted-jobs/claim",
                    "/my-items/saved-jobs",
                    "/comm/my-items/saved-jobs",
                    "/my-items/projects",
                    "/mycompany/*",
                    "/safety/reports",
                    "/safety/reports/*",
                    "/room/*",
                    "/rooms/*",
                    "/premium/news-onboarding",
                    "/comm/premium/news-onboarding",
                    "/comm/jobs/collections/*",
                    "/jobs/collections/*",
                    "/discover",
                    "/comm/discover",
                    "/suggested-for-you/*",
                    "/comm/suggested-for-you/*",
                    "/m/suggested-for-you/*",
                    "/comm/m/suggested-for-you/*"
                ]
            },
            {
                "appID": "8AXPVS6C36.com.linkedin.Zephyr",
                "paths": [
                    "/comm/m/",
                    "/comm/",
                    "/m/",
                    "/",
                    "/company/*",
                    "/e/v2/pulse",
                    "/e/v2/newsle",
                    "/comm/feed",
                    "/feed",
                    "/comm/m/feed",
                    "/m/feed",
                    "/comm/feed/share",
                    "/feed/share",
                    "/m/feed/share",
                    "/comm/m/feed/share",
                    "/feed/update/*",
                    "/comm/feed/update/*",
                    "/comm/m/feed/update/*",
                    "/m/feed/update/*",
                    "/comm/feed/update/*/likes",
                    "/feed/update/*/likes",
                    "/m/feed/update/*/likes",
                    "/comm/m/feed/update/*/likes",
                    "/comm/feed/update/*/reshare",
                    "/feed/update/*/reshare",
                    "/m/feed/update/*/reshare",
                    "/comm/m/feed/update/*/reshare",
                    "/feed/update/*/rmview",
                    "/comm/feed/update/*/rmview",
                    "/m/feed/update/*/rmview",
                    "/comm/m/feed/update/*/rmview",
                    "/feed/follow",
                    "/feed/follow/confirmation",
                    "/feed/news/*",
                    "/m/feed/news/*",
                    "/comm/feed/news/*",
                    "/comm/m/feed/news/*",
                    "/comm/news/story/*",
                    "/comm/m/news/story/*",
                    "/feed/topic/*",
                    "/m/feed/topic/*",
                    "/comm/feed/topic/*",
                    "/comm/m/feed/topic/*",
                    "/feed/hashtag/*",
                    "/m/feed/hashtag/*",
                    "/comm/feed/hashtag/*",
                    "/comm/m/feed/hashtag/*",
                    "/feed/sponsored-update/*",
                    "/fetch/enter-flow",
                    "/fetch/inviteAfterAcceptLanding",
                    "/comm/groups*",
                    "/groups*",
                    "/m/in/*",
                    "/comm/m/in/*",
                    "/in/*",
                    "/comm/in/*",
                    "/comm/job/home",
                    "/comm/jobs",
                    "/jobs",
                    "/jobs/saved",
                    "/jobs/career-interests",
                    "/jobs/launchpad-connect",
                    "/comm/jobs/launchpad-connect",
                    "/jobs/launchpad-success",
                    "/jobs/launchpad-update-profile",
                    "/comm/jobs/launchpad-update-profile",
                    "/jobs/search/onboarding-video",
                    "/comm/jobs/search/onboarding-video",
                    "/feed/launchpad",
                    "/comm/feed/launchpad",
                    "NOT /jobs/browse/*",
                    "/jobs/*-jobs",
                    "/jobs/*-jobs-*",
                    "/jobs/jobs-in-*",
                    "/jobs/referrals/*",
                    "/comm/jobs/referrals/*",
                    "/incareer/jobs/view/*",
                    "/comm/jobs/view/*",
                    "/jobs/view/*",
                    "/jobs2/view/*",
                    "/comm/jobs2/view/*",
                    "/jobs/search",
                    "/comm/jobs/search",
                    "/m/jobs/search",
                    "/comm/jobs/suggestions",
                    "/notifications",
                    "/comm/notifications",
                    "/notifications/*",
                    "/comm/notifications/*",
                    "/appreciation/*",
                    "/onboarding",
                    "/onboarding/start",
                    "/comm/people/invite-accept",
                    "/comm/people/invite-ignore",
                    "/people/pymk",
                    "/comm/people/pymk",
                    "/comm/people/pymk/hub",
                    "/people/pymk/hub",
                    "/comm/people/send-invite",
                    "/comm/mynetwork/discovery-see-all",
                    "/mynetwork/discovery-see-all",
                    "/comm/mynetwork/pymk/*",
                    "/comm/payments/reacquireV2",
                    "/payments/reacquireV2",
                    "/premium/products",
                    "/premium/my-premium",
                    "/premium/cancellation",
                    "/premium/redeem/promo",
                    "/premium/redeem/gift",
                    "/comm/premium/products",
                    "/comm/premium/my-premium",
                    "/comm/premium/cancellation",
                    "/comm/profile/*",
                    "/profinder/projects-notification/*",
                    "/comm/psettings/email/confirm",
                    "NOT /pulse/topics/*",
                    "/pulse/*",
                    "/comm/pulse/*",
                    "/reg/enter-flow",
                    "/settings/emailConfirm",
                    "/settings/darkmode",
                    "/start/",
                    "/wvmx/profile",
                    "/comm/wvmx/profile",
                    "comm/hp",
                    "comm/hp/update/*",
                    "comm/nhome",
                    "comm/nhome/updates",
                    "/m/company/*",
                    "company/*",
                    "/comm/company/*",
                    "/comm/m/company/*",
                    "/m/company-beta/*",
                    "/company-beta/*",
                    "comm/company-beta/*",
                    "comm/m/company-beta/*",
                    "feed-preferences/follow",
                    "feed-preferences",
                    "feed-preferences/unfollow",
                    "/comm/m/group/*",
                    "/comm/group/*",
                    "/m/group/*",
                    "group/*",
                    "groups/*",
                    "/m/groups/*",
                    "/comm/m/groups/*",
                    "hp",
                    "hp/update/*",
                    "/comm/m/job/*",
                    "job/*",
                    "/m/job/*",
                    "/comm/job/*",
                    "/m/job/home",
                    "/comm/m/job/home",
                    "job/home",
                    "launcher/xpromo_launcher_flagship",
                    "/comm/launcher/xpromo_launcher_flagship",
                    "/m/launcher/xpromo_launcher_flagship",
                    "/comm/m/launcher/xpromo_launcher_flagship",
                    "m/feed-preferences/follow",
                    "m/update/*",
                    "m/update/*/likes",
                    "m/update/*/reshare",
                    "m/update/*/rmview",
                    "/comm/me",
                    "/comm/m/me",
                    "me",
                    "/m/me",
                    "/m/me/profile-views",
                    "/me/profile-cover-story/create",
                    "/comm/me/profile-cover-story/create",
                    "/me/profile-video/create",
                    "/comm/me/profile-video/create",
                    "/comm/me/profile-views",
                    "me/profile-views",
                    "/comm/m/me/profile-views",
                    "me/recent-activity",
                    "/comm/me/recent-activity",
                    "/comm/m/me/recent-activity",
                    "/m/me/recent-activity",
                    "me/search-appearances",
                    "/m/me/search-appearances",
                    "/comm/me/search-appearances",
                    "/comm/messaging",
                    "/m/messaging",
                    "/comm/m/messaging",
                    "messaging",
                    "messaging/compose",
                    "/comm/messaging/compose",
                    "/comm/m/messaging/compose",
                    "/m/messaging/compose",
                    "/m/messaging/compose/*",
                    "/comm/messaging/compose/*",
                    "messaging/compose/*",
                    "/comm/m/messaging/compose/*",
                    "/comm/messaging/thread/*",
                    "/m/messaging/thread/*",
                    "messaging/thread/*",
                    "/comm/m/messaging/thread/*",
                    "/chat/*",
                    "/thread/*/conference/*",
                    "/comm/mynetwork",
                    "/m/mynetwork",
                    "/comm/m/mynetwork",
                    "mynetwork",
                    "mynetwork/heathrow-redirect",
                    "/comm/mynetwork/heathrow-redirect",
                    "/comm/m/mynetwork/heathrow-redirect",
                    "/m/mynetwork/heathrow-redirect",
                    "/comm/mynetwork/import-contacts",
                    "/comm/m/mynetwork/import-contacts",
                    "/m/mynetwork/import-contacts",
                    "mynetwork/import-contacts",
                    "/comm/mynetwork/import-contacts/results",
                    "/comm/m/mynetwork/import-contacts/results",
                    "/m/mynetwork/import-contacts/results",
                    "mynetwork/import-contacts/results",
                    "/comm/mynetwork/connection-suggestions",
                    "/comm/m/mynetwork/connection-suggestions",
                    "/m/mynetwork/connection-suggestions",
                    "mynetwork/connection-suggestions",
                    "/comm/m/mynetwork/invite-accept/invitationId/*/sharedKey/*",
                    "mynetwork/invite-accept/invitationId/*/sharedKey/*",
                    "/m/mynetwork/invite-accept/invitationId/*/sharedKey/*",
                    "/comm/mynetwork/invite-accept/invitationId/*/sharedKey/*",
                    "/comm/m/mynetwork/invite-ignore/invitationId/*/sharedKey/*",
                    "mynetwork/invite-ignore/invitationId/*/sharedKey/*",
                    "/m/mynetwork/invite-ignore/invitationId/*/sharedKey/*",
                    "/comm/mynetwork/invite-ignore/invitationId/*/sharedKey/*",
                    "/comm/m/mynetwork/send-invite/*",
                    "mynetwork/send-invite/*",
                    "/m/mynetwork/send-invite/*",
                    "/comm/mynetwork/send-invite/*",
                    "/build-relation",
                    "/build-relation/*",
                    "/comm/m/mynetwork/add-connections",
                    "mynetwork/add-connections",
                    "/m/mynetwork/add-connections",
                    "/comm/mynetwork/add-connections",
                    "mynetwork/invite-connect/connections",
                    "/m/mynetwork/invite-connect/connections",
                    "/comm/mynetwork/invite-connect/connections",
                    "/comm/m/mynetwork/invite-connect/connections",
                    "/m/mynetwork/invite-connect/invitations",
                    "/comm/m/mynetwork/invite-connect/invitations",
                    "mynetwork/invite-connect/invitations",
                    "/comm/mynetwork/invite-connect/invitations",
                    "mynetwork/discover-hub",
                    "/comm/mynetwork/discover-hub",
                    "nhome",
                    "nhome/updates",
                    "/m/profile/*",
                    "/comm/m/profile/*",
                    "/profile/*",
                    "/profile/add",
                    "/m/profile/add",
                    "/comm/m/profile/add",
                    "/m/profile/edit",
                    "/comm/m/profile/edit",
                    "profile/edit",
                    "/comm/profile/edit",
                    "/m/profile/uedit",
                    "/comm/m/profile/uedit",
                    "profile/uedit",
                    "/comm/profile/uedit",
                    "/m/profile/edit/skills",
                    "profile/edit/skills",
                    "/comm/m/profile/edit/skills",
                    "/comm/profile/edit/skills",
                    "/comm/m/profile/guided/*",
                    "profile/guided/*",
                    "/comm/profile/guided/*",
                    "/m/profile/guided/*",
                    "/m/profile/pendingEndorsements",
                    "/comm/profile/pendingEndorsements",
                    "/comm/m/profile/pendingEndorsements",
                    "profile/pendingEndorsements",
                    "/pub/dir/*",
                    "recs/received",
                    "/m/recs/received",
                    "/comm/m/recs/received",
                    "recs/give",
                    "/m/recs/give",
                    "/comm/m/recs/give",
                    "/profile-opportunities/job-opportunities",
                    "/comm/profile-opportunities/job-opportunities",
                    "/profile-opportunities/job-opportunities/edit",
                    "/comm/profile-opportunities/job-opportunities/edit",
                    "/comm/m/school/*",
                    "school/*",
                    "/comm/school/*",
                    "/m/school/*",
                    "/comm/settings",
                    "/comm/m/settings",
                    "/m/settings",
                    "settings",
                    "/comm/settings/messages",
                    "/comm/m/settings/messages",
                    "settings/messages",
                    "/m/settings/messages",
                    "settings/privacy",
                    "psettings/privacy",
                    "/m/settings/privacy",
                    "/comm/settings/privacy",
                    "/comm/m/settings/privacy",
                    "/comm/share",
                    "/comm/m/share",
                    "share",
                    "/m/share",
                    "shareArticle",
                    "/cws/share",
                    "update/*",
                    "/comm/update/*",
                    "/comm/m/update/*",
                    "/m/update/*",
                    "update/*/likes",
                    "/m/update/*/likes",
                    "/comm/m/update/*/likes",
                    "/comm/update/*/likes",
                    "/m/update/*/reshare",
                    "/comm/m/update/*/reshare",
                    "/comm/update/*/reshare",
                    "update/*/reshare",
                    "/comm/m/update/*/rmview",
                    "/m/update/*/rmview",
                    "/comm/update/*/rmview",
                    "update/*/rmview",
                    "search/results/all/*",
                    "/m/search/results/all/*",
                    "/comm/search/results/all/*",
                    "/comm/m/search/results/all/*",
                    "search/results/content/*",
                    "/m/search/results/content/*",
                    "/comm/search/results/content/*",
                    "/comm/m/search/results/content/*",
                    "search/results/people/*",
                    "/m/search/results/people/*",
                    "/comm/m/search/results/people/*",
                    "/comm/search/results/people/*",
                    "search/results/index/*",
                    "/m/search/results/index/*",
                    "/comm/m/search/results/index/*",
                    "/comm/search/results/index/*",
                    "NOT /wukong-web/companyReflection/list",
                    "NOT /wukong-web/companyReflection/companyList",
                    "/wukong-web/companyReflection/*",
                    "/wukong-web/zephyrDownload",
                    "/wukong-web/zephyrDownload/*",
                    "/wujing-frontend/ar2019_mid",
                    "/wujing-frontend/novaSignup",
                    "/wujing-frontend/novaRank",
                    "/wujing-frontend/novaArchive",
                    "/events/*",
                    "/comm/events/*",
                    "/video/collection/*",
                    "/comm/video/collection/*",
                    "/stories/*",
                    "/comm/stories/*",
                    "/signup/cold-join/*",
                    "/login/*",
                    "/wechat/*",
                    "/talent/post-a-job",
                    "/talent/compliance/dashboard",
                    "/services/page/*",
                    "/comm/services/page/*",
                    "/comm/jobs/collections/*",
                    "/jobs/collections/*"
                ]
            },
            {
                "appID": "277WVWYGVH.com.linkedin.Zephyr.enterprise",
                "paths": [
                    "/comm/m/",
                    "/comm/",
                    "/m/",
                    "/",
                    "/company/*",
                    "/e/v2/pulse",
                    "/e/v2/newsle",
                    "/comm/feed",
                    "/feed",
                    "/comm/m/feed",
                    "/m/feed",
                    "/comm/feed/share",
                    "/feed/share",
                    "/m/feed/share",
                    "/comm/m/feed/share",
                    "/feed/update/*",
                    "/comm/feed/update/*",
                    "/comm/m/feed/update/*",
                    "/m/feed/update/*",
                    "/comm/feed/update/*/likes",
                    "/feed/update/*/likes",
                    "/m/feed/update/*/likes",
                    "/comm/m/feed/update/*/likes",
                    "/comm/feed/update/*/reshare",
                    "/feed/update/*/reshare",
                    "/m/feed/update/*/reshare",
                    "/comm/m/feed/update/*/reshare",
                    "/feed/update/*/rmview",
                    "/comm/feed/update/*/rmview",
                    "/m/feed/update/*/rmview",
                    "/comm/m/feed/update/*/rmview",
                    "/feed/follow",
                    "/feed/follow/confirmation",
                    "/feed/news/*",
                    "/m/feed/news/*",
                    "/comm/feed/news/*",
                    "/comm/m/feed/news/*",
                    "/comm/news/story/*",
                    "/comm/m/news/story/*",
                    "/feed/topic/*",
                    "/m/feed/topic/*",
                    "/comm/feed/topic/*",
                    "/comm/m/feed/topic/*",
                    "/feed/hashtag/*",
                    "/m/feed/hashtag/*",
                    "/comm/feed/hashtag/*",
                    "/comm/m/feed/hashtag/*",
                    "/feed/sponsored-update/*",
                    "/fetch/enter-flow",
                    "/fetch/inviteAfterAcceptLanding",
                    "/comm/groups*",
                    "/groups*",
                    "/m/in/*",
                    "/comm/m/in/*",
                    "/in/*",
                    "/comm/in/*",
                    "/comm/job/home",
                    "/comm/jobs",
                    "/jobs",
                    "/jobs/saved",
                    "/jobs/career-interests",
                    "/jobs/launchpad-connect",
                    "/comm/jobs/launchpad-connect",
                    "/jobs/launchpad-success",
                    "/jobs/launchpad-update-profile",
                    "/comm/jobs/launchpad-update-profile",
                    "/jobs/search/onboarding-video",
                    "/comm/jobs/search/onboarding-video",
                    "/feed/launchpad",
                    "/comm/feed/launchpad",
                    "NOT /jobs/browse/*",
                    "/jobs/*-jobs",
                    "/jobs/*-jobs-*",
                    "/jobs/jobs-in-*",
                    "/jobs/referrals/*",
                    "/comm/jobs/referrals/*",
                    "/incareer/jobs/view/*",
                    "/comm/jobs/view/*",
                    "/jobs/view/*",
                    "/jobs2/view/*",
                    "/comm/jobs2/view/*",
                    "/jobs/search",
                    "/comm/jobs/search",
                    "/m/jobs/search",
                    "/comm/jobs/suggestions",
                    "/notifications",
                    "/comm/notifications",
                    "/notifications/*",
                    "/comm/notifications/*",
                    "/appreciation/*",
                    "/onboarding",
                    "/onboarding/start",
                    "/comm/people/invite-accept",
                    "/comm/people/invite-ignore",
                    "/people/pymk",
                    "/comm/people/pymk",
                    "/comm/people/pymk/hub",
                    "/people/pymk/hub",
                    "/comm/people/send-invite",
                    "/comm/mynetwork/discovery-see-all",
                    "/mynetwork/discovery-see-all",
                    "/comm/mynetwork/discover-hub",
                    "/comm/mynetwork/pymk/*",
                    "mynetwork/discover-hub",
                    "/comm/payments/reacquireV2",
                    "/payments/reacquireV2",
                    "/premium/products",
                    "/premium/my-premium",
                    "/premium/cancellation",
                    "/premium/redeem/promo",
                    "/premium/redeem/gift",
                    "/comm/premium/products",
                    "/comm/premium/my-premium",
                    "/comm/premium/cancellation",
                    "/comm/profile/*",
                    "/profinder/projects-notification/*",
                    "/comm/psettings/email/confirm",
                    "NOT /pulse/topics/*",
                    "/pulse/*",
                    "/comm/pulse/*",
                    "/reg/enter-flow",
                    "/settings/emailConfirm",
                    "/settings/darkmode",
                    "/start/",
                    "/wvmx/profile",
                    "/comm/wvmx/profile",
                    "comm/hp",
                    "comm/hp/update/*",
                    "comm/nhome",
                    "comm/nhome/updates",
                    "/m/company/*",
                    "company/*",
                    "/comm/company/*",
                    "/comm/m/company/*",
                    "/m/company-beta/*",
                    "/company-beta/*",
                    "comm/company-beta/*",
                    "comm/m/company-beta/*",
                    "feed-preferences/follow",
                    "feed-preferences",
                    "feed-preferences/unfollow",
                    "/comm/m/group/*",
                    "/comm/group/*",
                    "/m/group/*",
                    "group/*",
                    "groups/*",
                    "/m/groups/*",
                    "/comm/m/groups/*",
                    "hp",
                    "hp/update/*",
                    "/comm/m/job/*",
                    "job/*",
                    "/m/job/*",
                    "/comm/job/*",
                    "/m/job/home",
                    "/comm/m/job/home",
                    "job/home",
                    "launcher/xpromo_launcher_flagship",
                    "/comm/launcher/xpromo_launcher_flagship",
                    "/m/launcher/xpromo_launcher_flagship",
                    "/comm/m/launcher/xpromo_launcher_flagship",
                    "m/feed-preferences/follow",
                    "m/update/*",
                    "m/update/*/likes",
                    "m/update/*/reshare",
                    "m/update/*/rmview",
                    "/comm/me",
                    "/comm/m/me",
                    "me",
                    "/m/me",
                    "/m/me/profile-views",
                    "/me/profile-cover-story/create",
                    "/comm/me/profile-cover-story/create",
                    "/me/profile-video/create",
                    "/comm/me/profile-video/create",
                    "/comm/me/profile-views",
                    "me/profile-views",
                    "/comm/m/me/profile-views",
                    "me/recent-activity",
                    "/comm/me/recent-activity",
                    "/comm/m/me/recent-activity",
                    "/m/me/recent-activity",
                    "me/search-appearances",
                    "/m/me/search-appearances",
                    "/comm/me/search-appearances",
                    "/comm/messaging",
                    "/m/messaging",
                    "/comm/m/messaging",
                    "messaging",
                    "messaging/compose",
                    "/comm/messaging/compose",
                    "/comm/m/messaging/compose",
                    "/m/messaging/compose",
                    "/m/messaging/compose/*",
                    "/comm/messaging/compose/*",
                    "messaging/compose/*",
                    "/comm/m/messaging/compose/*",
                    "/comm/messaging/thread/*",
                    "/m/messaging/thread/*",
                    "messaging/thread/*",
                    "/comm/m/messaging/thread/*",
                    "/chat/*",
                    "/thread/*/conference/*",
                    "/comm/mynetwork",
                    "/m/mynetwork",
                    "/comm/m/mynetwork",
                    "mynetwork",
                    "mynetwork/heathrow-redirect",
                    "/comm/mynetwork/heathrow-redirect",
                    "/comm/m/mynetwork/heathrow-redirect",
                    "/m/mynetwork/heathrow-redirect",
                    "/comm/mynetwork/import-contacts",
                    "/comm/m/mynetwork/import-contacts",
                    "/m/mynetwork/import-contacts",
                    "mynetwork/import-contacts",
                    "/comm/mynetwork/import-contacts/results",
                    "/comm/m/mynetwork/import-contacts/results",
                    "/m/mynetwork/import-contacts/results",
                    "mynetwork/import-contacts/results",
                    "/comm/mynetwork/connection-suggestions",
                    "/comm/m/mynetwork/connection-suggestions",
                    "/m/mynetwork/connection-suggestions",
                    "mynetwork/connection-suggestions",
                    "/comm/m/mynetwork/invite-accept/invitationId/*/sharedKey/*",
                    "mynetwork/invite-accept/invitationId/*/sharedKey/*",
                    "/m/mynetwork/invite-accept/invitationId/*/sharedKey/*",
                    "/comm/mynetwork/invite-accept/invitationId/*/sharedKey/*",
                    "/comm/m/mynetwork/invite-ignore/invitationId/*/sharedKey/*",
                    "mynetwork/invite-ignore/invitationId/*/sharedKey/*",
                    "/m/mynetwork/invite-ignore/invitationId/*/sharedKey/*",
                    "/comm/mynetwork/invite-ignore/invitationId/*/sharedKey/*",
                    "/comm/m/mynetwork/send-invite/*",
                    "mynetwork/send-invite/*",
                    "/m/mynetwork/send-invite/*",
                    "/comm/mynetwork/send-invite/*",
                    "/build-relation",
                    "/build-relation/*",
                    "/comm/m/mynetwork/add-connections",
                    "mynetwork/add-connections",
                    "/m/mynetwork/add-connections",
                    "/comm/mynetwork/add-connections",
                    "mynetwork/invite-connect/connections",
                    "/m/mynetwork/invite-connect/connections",
                    "/comm/mynetwork/invite-connect/connections",
                    "/comm/m/mynetwork/invite-connect/connections",
                    "/m/mynetwork/invite-connect/invitations",
                    "/comm/m/mynetwork/invite-connect/invitations",
                    "mynetwork/invite-connect/invitations",
                    "/comm/mynetwork/invite-connect/invitations",
                    "nhome",
                    "nhome/updates",
                    "/m/profile/*",
                    "/comm/m/profile/*",
                    "/profile/*",
                    "/profile/add",
                    "/m/profile/add",
                    "/comm/m/profile/add",
                    "/m/profile/edit",
                    "/comm/m/profile/edit",
                    "profile/edit",
                    "/comm/profile/edit",
                    "/m/profile/uedit",
                    "/comm/m/profile/uedit",
                    "profile/uedit",
                    "/comm/profile/uedit",
                    "/m/profile/edit/skills",
                    "profile/edit/skills",
                    "/comm/m/profile/edit/skills",
                    "/comm/profile/edit/skills",
                    "/comm/m/profile/guided/*",
                    "profile/guided/*",
                    "/comm/profile/guided/*",
                    "/m/profile/guided/*",
                    "/m/profile/pendingEndorsements",
                    "/comm/profile/pendingEndorsements",
                    "/comm/m/profile/pendingEndorsements",
                    "profile/pendingEndorsements",
                    "/pub/dir/*",
                    "recs/received",
                    "/m/recs/received",
                    "/comm/m/recs/received",
                    "recs/give",
                    "/m/recs/give",
                    "/comm/m/recs/give",
                    "/profile-opportunities/job-opportunities",
                    "/comm/profile-opportunities/job-opportunities",
                    "/profile-opportunities/job-opportunities/edit",
                    "/comm/profile-opportunities/job-opportunities/edit",
                    "/comm/m/school/*",
                    "school/*",
                    "/comm/school/*",
                    "/m/school/*",
                    "/comm/settings",
                    "/comm/m/settings",
                    "/m/settings",
                    "settings",
                    "/comm/settings/messages",
                    "/comm/m/settings/messages",
                    "settings/messages",
                    "/m/settings/messages",
                    "settings/privacy",
                    "psettings/privacy",
                    "/m/settings/privacy",
                    "/comm/settings/privacy",
                    "/comm/m/settings/privacy",
                    "/comm/share",
                    "/comm/m/share",
                    "share",
                    "/m/share",
                    "shareArticle",
                    "/cws/share",
                    "update/*",
                    "/comm/update/*",
                    "/comm/m/update/*",
                    "/m/update/*",
                    "update/*/likes",
                    "/m/update/*/likes",
                    "/comm/m/update/*/likes",
                    "/comm/update/*/likes",
                    "/m/update/*/reshare",
                    "/comm/m/update/*/reshare",
                    "/comm/update/*/reshare",
                    "update/*/reshare",
                    "/comm/m/update/*/rmview",
                    "/m/update/*/rmview",
                    "/comm/update/*/rmview",
                    "update/*/rmview",
                    "search/results/all/*",
                    "/m/search/results/all/*",
                    "/comm/search/results/all/*",
                    "/comm/m/search/results/all/*",
                    "search/results/content/*",
                    "/m/search/results/content/*",
                    "/comm/search/results/content/*",
                    "/comm/m/search/results/content/*",
                    "search/results/people/*",
                    "/m/search/results/people/*",
                    "/comm/m/search/results/people/*",
                    "/comm/search/results/people/*",
                    "search/results/index/*",
                    "/m/search/results/index/*",
                    "/comm/m/search/results/index/*",
                    "/comm/search/results/index/*",
                    "NOT /wukong-web/companyReflection/list",
                    "NOT /wukong-web/companyReflection/companyList",
                    "/wukong-web/companyReflection/*",
                    "/wukong-web/zephyrDownload",
                    "/wukong-web/zephyrDownload/*",
                    "/wujing-frontend/ar2019_mid",
                    "/wujing-frontend/novaSignup",
                    "/wujing-frontend/novaRank",
                    "/wujing-frontend/novaArchive",
                    "/events/*",
                    "/comm/events/*",
                    "/video/collection/*",
                    "/comm/video/collection/*",
                    "/stories/*",
                    "/comm/stories/*",
                    "/signup/cold-join/*",
                    "/login/*",
                    "/wechat_ent/*",
                    "/services/page/*",
                    "/comm/services/page/*",
                    "/comm/jobs/collections/*",
                    "/jobs/collections/*"
                ]
            },
            {
                "appID": "277WVWYGVH.com.linkedin.pulse.enterprise",
                "paths": [
                    "/pulse/*",
                    "/comm/pulse/*",
                    "/e/v2/pulse",
                    "/e/v2/newsle"
                ]
            },
            {
                "appID": "8AXPVS6C36.com.linkedin.pulse",
                "paths": [
                    "/pulse/*",
                    "/comm/pulse/*",
                    "/e/v2/pulse/*"
                ]
            },
            {
                "appID": "277WVWYGVH.com.linkedin.Learning.enterprise",
                "paths": [
                    "NOT /learning/frame/*",
                    "/learning/*",
                    "/learning-login/share",
                    "/comm/learning/*"
                ]
            },
            {
                "appID": "8AXPVS6C36.com.linkedin.Learning",
                "paths": [
                    "NOT /learning/frame/*",
                    "/learning/*",
                    "/learning-login/share",
                    "/comm/learning/*"
                ]
            },
            {
                "appID": "8AXPVS6C36.com.linkedin.universallinktest",
                "paths": [
                    "/ultest/*"
                ]
            }
        ]
    },
    "webcredentials": {
        "apps": [
            "8AXPVS6C36.com.linkedin.LinkedIn",
            "277WVWYGVH.com.linkedin.LinkedIn",
            "277WVWYGVH.com.linkedin.LinkedIn.enterprise",
            "8AXPVS6C36.com.linkedin.Learning",
            "8AXPVS6C36.com.linkedin.Lighthouse",
            "277WVWYGVH.com.linkedin.LighthouseEnterprise",
            "8AXPVS6C36.com.linkedin.recruiter",
            "64ZXQ8664V.com.linkedin.recruiter.enterprise",
            "8AXPVS6C36.com.linkedin.Zephyr",
            "277WVWYGVH.com.linkedin.Zephyr.enterprise"
        ]
    },
    "activitycontinuation": {
        "apps": [
            "277WVWYGVH.com.linkedin.LinkedIn",
            "277WVWYGVH.com.linkedin.LinkedIn.enterprise"
        ]
    }
}